.gitignore
MANIFEST.in
README.rst
bootstrap.py
buildout.cfg
setup.py
collective/__init__.py
collective.registry.egg-info/PKG-INFO
collective.registry.egg-info/SOURCES.txt
collective.registry.egg-info/dependency_links.txt
collective.registry.egg-info/entry_points.txt
collective.registry.egg-info/namespace_packages.txt
collective.registry.egg-info/not-zip-safe
collective.registry.egg-info/requires.txt
collective.registry.egg-info/top_level.txt
collective/registry/__init__.py
collective/registry/configure.zcml
collective/registry/contextual_registry.py
collective/registry/tests/__init__.py
docs/HISTORY.txt
docs/INSTALL.txt
docs/LICENSE.GPL
docs/LICENSE.txt