Metadata-Version: 1.0
Name: collective.registry
Version: 1.0
Summary: Extend plone.app.registry by implementing IRegistry with an adapter on context
Home-page: https://github.com/collective/collective.registry
Author: Jean-Michel FRANCOIS (toutpt)
Author-email: toutpt@gmail.com
License: GPL
Keywords: plone registry
Platform: UNKNOWN
Classifier: Framework :: Plone
Classifier: Framework :: Plone :: 4.0
Classifier: Framework :: Plone :: 4.1
Classifier: Programming Language :: Python
